Workbook
Name DSCR: Debt_Schedule!$G$2:$G$16

Sheet Inputs
A1: Item | B1: Value
A2: Project life | B2: 15 years
A3: Construction period | B3: 1 year
A4: Debt tenor | B4: 12 years
A5: Interest rate | B5: 0.0625
A6: Target DSCR | B6: 1.3
A7: Opening debt balance | B7: 120000000
A8: Corporate tax | B8: 0

Sheet Operating_Cashflows
A1: Year | B1: Revenue | C1: OpEx | D1: Maintenance
A2: 1 | B2: 0 | C2: 0 | D2: 0
A3: 2 | B3: 22500000 | C3: 5200000 | D3: 800000
A4: 3 | B4: 23000000 | C4: 5300000 | D4: 820000
A5: 4 | B5: 23200000 | C5: 5400000 | D5: 840000
A6: 5 | B6: 23600000 | C6: 5500000 | D6: 860000
A7: 6 | B7: 23700000 | C7: 5600000 | D7: 880000
A8: 7 | B8: 24000000 | C8: 5700000 | D8: 900000
A9: 8 | B9: 23650000 | C9: 5800000 | D9: 900000
A10: 9 | B10: 24228571 | C10: 5900000 | D10: 900000
A11: 10 | B11: 24441071 | C11: 5900000 | D11: 900000
A12: 11 | B12: 24653571 | C12: 5900000 | D12: 900000
A13: 12 | B13: 24866071 | C13: 5900000 | D13: 900000
... A16: 15 | B16: 25503571 | C16: 5900000 | D16: 900000

Sheet Debt_Schedule
A1: Year | B1: Opening Debt | C1: CFADS | D1: Interest | E1: Principal | F1: Debt Service | G1: DSCR | H1: Closing Debt | I1: Cash sweep
A2: 1 | B2: =Inputs!B7 -> 120000000 | C2: =_xlfn.LET(_xlpm.Revenue, Operating_Cashflows!B3, _xlpm.opEx, Operating_Cashflows!C3, _xlpm.Maintenance, Operating_Cashflows!D3, _xlpm.Revenue - _xlpm.opEx - _xlpm.Maintenance) -> 16500000 | D2: =Inputs!$B$7*Inputs!$B$5 -> 7500000 | E2: =F2-D2 -> 5192307.7 | F2: =_xlfn.LET(_xlpm.CFADS, C2, _xlpm.TargetDSCR, Inputs!$B$6, (_xlpm.CFADS/_xlpm.TargetDSCR)) -> 12692308 | G2: =C2/F2 -> 1.3 | I2: {=_xlfn.MAP(C2:C16, F2:F16, G2:G16, _xlfn.LAMBDA(_xlpm.cfads,_xlpm.debt_service,_xlpm.dscr, _xlfn.LET(_xlpm.ExcessCash, _xlpm.cfads - _xlpm.debt_service, _xlpm.LockUpDSCR, 1.2, _xlpm.DSCRthreshold, _xlpm.dscr, _xlpm.Sweep_Percentage, 0.75, IF(_xlpm.DSCRthreshold > _xlpm.LockUpDSCR, _xlpm.ExcessCash * _xlpm.Sweep_Percentage, 0))))} -> 2855769.2
A3: 2 | C3: =_xlfn.LET(_xlpm.Revenue, Operating_Cashflows!B3, _xlpm.opEx, Operating_Cashflows!C3, _xlpm.Maintenance, Operating_Cashflows!D3, _xlpm.Revenue - _xlpm.opEx - _xlpm.Maintenance) -> 16500000 | D3: =Inputs!$B$7*Inputs!$B$5 -> 7500000 | E3: =F3-D3 -> 5192307.7 | F3: =_xlfn.LET(_xlpm.CFADS, C3, _xlpm.TargetDSCR, Inputs!$B$6, (_xlpm.CFADS/_xlpm.TargetDSCR)) -> 12692308 | G3: =C3/F3 -> 1.3 | I3: 2855769.2
A4: 3 | C4: =_xlfn.LET(_xlpm.Revenue, Operating_Cashflows!B4, _xlpm.opEx, Operating_Cashflows!C4, _xlpm.Maintenance, Operating_Cashflows!D4, _xlpm.Revenue - _xlpm.opEx - _xlpm.Maintenance) -> 16880000 | D4: =Inputs!$B$7*Inputs!$B$5 -> 7500000 | E4: =F4-D4 -> 5484615.4 | F4: =_xlfn.LET(_xlpm.CFADS, C4, _xlpm.TargetDSCR, Inputs!$B$6, (_xlpm.CFADS/_xlpm.TargetDSCR)) -> 12984615 | G4: =C4/F4 -> 1.3 | I4: 2921538.5
A5: 4 | C5: =_xlfn.LET(_xlpm.Revenue, Operating_Cashflows!B5, _xlpm.opEx, Operating_Cashflows!C5, _xlpm.Maintenance, Operating_Cashflows!D5, _xlpm.Revenue - _xlpm.opEx - _xlpm.Maintenance) -> 16960000 | D5: =Inputs!$B$7*Inputs!$B$5 -> 7500000 | E5: =F5-D5 -> 5546153.8 | F5: =_xlfn.LET(_xlpm.CFADS, C5, _xlpm.TargetDSCR, Inputs!$B$6, (_xlpm.CFADS/_xlpm.TargetDSCR)) -> 13046154 | G5: =C5/F5 -> 1.3 | I5: 2935384.6
A6: 5 | C6: =_xlfn.LET(_xlpm.Revenue, Operating_Cashflows!B6, _xlpm.opEx, Operating_Cashflows!C6, _xlpm.Maintenance, Operating_Cashflows!D6, _xlpm.Revenue - _xlpm.opEx - _xlpm.Maintenance) -> 17240000 | D6: =Inputs!$B$7*Inputs!$B$5 -> 7500000 | E6: =F6-D6 -> 5761538.5 | F6: =_xlfn.LET(_xlpm.CFADS, C6, _xlpm.TargetDSCR, Inputs!$B$6, (_xlpm.CFADS/_xlpm.TargetDSCR)) -> 13261538 | G6: =C6/F6 -> 1.3 | I6: 2983846.2
A7: 6 | C7: =_xlfn.LET(_xlpm.Revenue, Operating_Cashflows!B7, _xlpm.opEx, Operating_Cashflows!C7, _xlpm.Maintenance, Operating_Cashflows!D7, _xlpm.Revenue - _xlpm.opEx - _xlpm.Maintenance) -> 17220000 | D7: =Inputs!$B$7*Inputs!$B$5 -> 7500000 | E7: =F7-D7 -> 5746153.8 | F7: =_xlfn.LET(_xlpm.CFADS, C7, _xlpm.TargetDSCR, Inputs!$B$6, (_xlpm.CFADS/_xlpm.TargetDSCR)) -> 13246154 | G7: =C7/F7 -> 1.3 | I7: 2980384.6
A8: 7 | C8: =_xlfn.LET(_xlpm.Revenue, Operating_Cashflows!B8, _xlpm.opEx, Operating_Cashflows!C8, _xlpm.Maintenance, Operating_Cashflows!D8, _xlpm.Revenue - _xlpm.opEx - _xlpm.Maintenance) -> 17400000 | D8: =Inputs!$B$7*Inputs!$B$5 -> 7500000 | E8: =F8-D8 -> 5884615.4 | F8: =_xlfn.LET(_xlpm.CFADS, C8, _xlpm.TargetDSCR, Inputs!$B$6, (_xlpm.CFADS/_xlpm.TargetDSCR)) -> 13384615 | G8: =C8/F8 -> 1.3 | I8: 3011538.5
A9: 8 | C9: =_xlfn.LET(_xlpm.Revenue, Operating_Cashflows!B9, _xlpm.opEx, Operating_Cashflows!C9, _xlpm.Maintenance, Operating_Cashflows!D9, _xlpm.Revenue - _xlpm.opEx - _xlpm.Maintenance) -> 16950000 | D9: =Inputs!$B$7*Inputs!$B$5 -> 7500000 | E9: =F9-D9 -> 5538461.5 | F9: =_xlfn.LET(_xlpm.CFADS, C9, _xlpm.TargetDSCR, Inputs!$B$6, (_xlpm.CFADS/_xlpm.TargetDSCR)) -> 13038462 | G9: =C9/F9 -> 1.3 | I9: 2933653.8
A10: 9 | C10: =_xlfn.LET(_xlpm.Revenue, Operating_Cashflows!B10, _xlpm.opEx, Operating_Cashflows!C10, _xlpm.Maintenance, Operating_Cashflows!D10, _xlpm.Revenue - _xlpm.opEx - _xlpm.Maintenance) -> 17428571 | D10: =Inputs!$B$7*Inputs!$B$5 -> 7500000 | E10: =F10-D10 -> 5906593.4 | F10: =_xlfn.LET(_xlpm.CFADS, C10, _xlpm.TargetDSCR, Inputs!$B$6, (_xlpm.CFADS/_xlpm.TargetDSCR)) -> 13406593 | G10: =C10/F10 -> 1.3 | I10: 3016483.5
A11: 10 | C11: =_xlfn.LET(_xlpm.Revenue, Operating_Cashflows!B11, _xlpm.opEx, Operating_Cashflows!C11, _xlpm.Maintenance, Operating_Cashflows!D11, _xlpm.Revenue - _xlpm.opEx - _xlpm.Maintenance) -> 17641071 | D11: =Inputs!$B$7*Inputs!$B$5 -> 7500000 | E11: =F11-D11 -> 6070054.9 | F11: =_xlfn.LET(_xlpm.CFADS, C11, _xlpm.TargetDSCR, Inputs!$B$6, (_xlpm.CFADS/_xlpm.TargetDSCR)) -> 13570055 | G11: =C11/F11 -> 1.3 | I11: 3053262.4
A12: 11 | C12: =_xlfn.LET(_xlpm.Revenue, Operating_Cashflows!B12, _xlpm.opEx, Operating_Cashflows!C12, _xlpm.Maintenance, Operating_Cashflows!D12, _xlpm.Revenue - _xlpm.opEx - _xlpm.Maintenance) -> 17853571 | D12: =Inputs!$B$7*Inputs!$B$5 -> 7500000 | E12: =F12-D12 -> 6233516.5 | F12: =_xlfn.LET(_xlpm.CFADS, C12, _xlpm.TargetDSCR, Inputs!$B$6, (_xlpm.CFADS/_xlpm.TargetDSCR)) -> 13733516 | G12: =C12/F12 -> 1.3 | I12: 3090041.2
A13: 12 | C13: =_xlfn.LET(_xlpm.Revenue, Operating_Cashflows!B13, _xlpm.opEx, Operating_Cashflows!C13, _xlpm.Maintenance, Operating_Cashflows!D13, _xlpm.Revenue - _xlpm.opEx - _xlpm.Maintenance) -> 18066071 | D13: =Inputs!$B$7*Inputs!$B$5 -> 7500000 | E13: =F13-D13 -> 6396978 | F13: =_xlfn.LET(_xlpm.CFADS, C13, _xlpm.TargetDSCR, Inputs!$B$6, (_xlpm.CFADS/_xlpm.TargetDSCR)) -> 13896978 | G13: =C13/F13 -> 1.3 | I13: 3126820.1
A14: 13 | C14: =_xlfn.LET(_xlpm.Revenue, Operating_Cashflows!B14, _xlpm.opEx, Operating_Cashflows!C14, _xlpm.Maintenance, Operating_Cashflows!D14, _xlpm.Revenue - _xlpm.opEx - _xlpm.Maintenance) -> 18278571 | D14: =Inputs!$B$7*Inputs!$B$5 -> 7500000 | E14: =F14-D14 -> 6560439.6 | F14: =_xlfn.LET(_xlpm.CFADS, C14, _xlpm.TargetDSCR, Inputs!$B$6, (_xlpm.CFADS/_xlpm.TargetDSCR)) -> 14060440 | G14: =C14/F14 -> 1.3 | I14: 3163598.9
A15: 14 | C15: =_xlfn.LET(_xlpm.Revenue, Operating_Cashflows!B15, _xlpm.opEx, Operating_Cashflows!C15, _xlpm.Maintenance, Operating_Cashflows!D15, _xlpm.Revenue - _xlpm.opEx - _xlpm.Maintenance) -> 18491071 | D15: =Inputs!$B$7*Inputs!$B$5 -> 7500000 | E15: =F15-D15 -> 6723901.1 | F15: =_xlfn.LET(_xlpm.CFADS, C15, _xlpm.TargetDSCR, Inputs!$B$6, (_xlpm.CFADS/_xlpm.TargetDSCR)) -> 14223901 | G15: =C15/F15 -> 1.3 | I15: 3200377.7
A16: 15 | C16: =_xlfn.LET(_xlpm.Revenue, Operating_Cashflows!B16, _xlpm.opEx, Operating_Cashflows!C16, _xlpm.Maintenance, Operating_Cashflows!D16, _xlpm.Revenue - _xlpm.opEx - _xlpm.Maintenance) -> 18703571 | D16: =Inputs!$B$7*Inputs!$B$5 -> 7500000 | E16: =F16-D16 -> 6887362.6 | F16: =_xlfn.LET(_xlpm.CFADS, C16, _xlpm.TargetDSCR, Inputs!$B$6, (_xlpm.CFADS/_xlpm.TargetDSCR)) -> 14387363 | G16: =C16/F16 -> 1.3 | H16: =B2-SUM(E2:E16) -> 30875000 | I16: 3237156.6
A18: TOTAL : | B18: =B2 -> 120000000 | C18: =SUM(C2:C16) -> 2.621125e+08 | D18: =SUM(D2:D16) -> 112500000 | E18: =SUM(E2:E16) -> 89125000 | F18: =SUM(F2:F16) -> 2.01625e+08 | G18: =G16 -> 1.3 | H18: =H16 -> 30875000 | I18: =_xlfn.LET(_xlpm.ExcessCash, C18-F18, _xlpm.LockUpThresh, 1.2, _xlpm.DSCR, 1.3, _xlpm.Sweep_Percentage, 0.75, IF(_xlpm.DSCR > _xlpm.LockUpThresh, _xlpm.ExcessCash * _xlpm.Sweep_Percentage, 0)) -> 45365625

Sheet Debt checks
B2: DSCR consistency check | D2: Cash leakage check | F2: Debt fully repaid check | H2: Lock-up trigger
B4: {=_xlfn.LET(_xlpm.Target_DSCR, Inputs!B6, MAX(ABS(Debt_Schedule!G2:G15 - _xlpm.Target_DSCR)) < 0.01)} -> TRUE | D4: =Debt_Schedule!C16-Debt_Schedule!F16 >= 0 -> TRUE | F4: =Debt_Schedule!H16=0 -> FALSE | H4: =IF(Debt_Schedule!G16 < 1.2, "LOCKED", "OK") -> OK

Sheet Summary
A1: ="Airport Debt Summary - Base Case" & CHAR(10) -> Airport Debt Summary - Base Case
A2: ="Debt Overview" & CHAR(10) -> Debt Overview
A3: ="The project is financed with a senior amortising facility with an initial principal of " & TEXT(Debt_Schedule!B2, "#,##0 $") & ", target DSCR of " & TEXT(Inputs!B6, "0.00x") & " over period of " & Inputs!B4 & " . Debt service is fully supported by project CFADS throughout the operating period." & CHAR(10) & CHAR(10) -> The project is financed with a senior amortising facility with an initial principal of 120,000,000 $, target DSCR of 1.30x over period of 12 years . Debt service is fully supported by project CFADS throughout the operating period.
A5: ="Cash Flow & Debt Service Performance" & CHAR(10) -> Cash Flow & Debt Service Performance
A6: ="Across the life of the debt, the project generates cumulative CFADS of " & TEXT(Debt_Schedule!C18, "#,##0 $") & ", compared to total debt service obligations of " & TEXT(Debt_Schedule!F18, "#,##0 $") & CHAR(10) -> Across the life of the debt, the project generates cumulative CFADS of 262,112,500 $, compared to total debt service obligations of 201,625,000 $
A7: ="Interest payments amount to " & TEXT(Debt_Schedule!D18, "#,##0 $") & " over the tenor, while cumulative principal repayments reach " & TEXT(Debt_Schedule!E18, "#,##0 $") & ", supported by recurring cash sweeps totaling " & TEXT(Debt_Schedule!I18, "#,##0 $") & "." & CHAR(10) & CHAR(10) -> Interest payments amount to 112,500,000 $ over the tenor, while cumulative principal repayments reach 89,125,000 $, supported by recurring cash sweeps totaling 45,365,625 $.
A9: ="Amortisation & Residual Risk" & CHAR(10) -> Amortisation & Residual Risk
A10: ="Despite regular scheduled amortisation and excess cash application, the facility is not fully repaid at maturity, leaving a residual outstanding balance of " & TEXT(Debt_Schedule!H18, "#,##0 $") & " in the final year. This residual exposure represents a refinancing or balloon risk that must be addressed through refinancing, extension, or equity support." & CHAR(10) & CHAR(10) -> Despite regular scheduled amortisation and excess cash application, the facility is not fully repaid at maturity, leaving a residual outstanding balance of 30,875,000 $ in the final year. This residual exposure represents a refinancing or balloon risk that must be addressed through refinancing, extension, or equity support.
A12: ="Covenant & Structural Checks" & CHAR(10) -> Covenant & Structural Checks
A13: ="DSCR compliance: " & 'Debt checks'!B4 & CHAR(10) -> DSCR compliance: TRUE
A14: ="Cash leakage: " & 'Debt checks'!D4 & CHAR(10) -> Cash leakage: TRUE
A15: ="Debt fully repaid: " & 'Debt checks'!F4 & CHAR(10) -> Debt fully repaid: FALSE
A16: ="Lock-up trigger status: " & 'Debt checks'!H4 & CHAR(10) -> Lock-up trigger status: OK
A17: ="No DSCR breaches are observed in the base case, and no structural cash leakage is identified. However, the presence of a material terminal balance indicates lender exposure beyond the base operating cash flows." & CHAR(10) & CHAR(10) -> No DSCR breaches are observed in the base case, and no structural cash leakage is identified. However, the presence of a material terminal balance indicates lender exposure beyond the base operating cash flows.
A19: ="Credit Assessment (Lender View)" & CHAR(10) -> Credit Assessment (Lender View)
A20: ="✔ Strong and stable DSCR profile throughout the tenor" & CHAR(10) -> ✔ Strong and stable DSCR profile throughout the tenor
A21: ="✔ Consistent cash generation with surplus applied via cash sweep" & CHAR(10) -> ✔ Consistent cash generation with surplus applied via cash sweep
A22: ="⚠ Material residual debt at maturity (" & TEXT(Debt_Schedule!H18, "#,##0 $") & ")" & CHAR(10) -> ⚠ Material residual debt at maturity (30,875,000 $)
A23: ="⚠ Reliance on refinancing or terminal value realization" & CHAR(10) & CHAR(10) -> ⚠ Reliance on refinancing or terminal value realization
A25: ="Conclusion: The structure is creditworthy from a cash flow coverage perspective but exhibits balloon risk, which should be mitigated via refinancing assumptions, DSRA sizing, or increased amortisation under stress cases." -> Conclusion: The structure is creditworthy from a cash flow coverage perspective but exhibits balloon risk, which should be mitigated via refinancing assumptions, DSRA sizing, or increased amortisation under stress cases.
